kStatistics/__init__.py
kStatistics/main.py
kStatistics-1.0.dist-info/METADATA
kStatistics-1.0.dist-info/WHEEL
kStatistics-1.0.dist-info/top_level.txt
kStatistics-1.0.dist-info/RECORD
