Metadata-Version: 2.1
Name: kStatistics
Version: 1.0
